create_machine_utils/__init__.py
create_machine_utils/classes.py
create_machine_utils/decorators.py
create_machine_utils/data/__init__.py
create_machine_utils/data/json.py
create_machine_utils/minidiscord/__init__.py
create_machine_utils/minidiscord/context.py
create_machine_utils/minidiscord/errors.py
create_machine_utils/minidiscord/exceptions.py
create_machine_utils/minidiscord/input.py
create_machine_utils/minidiscord/menus.py
create_machine_utils/minidiscord/handlers/ArgumentErrors.py
create_machine_utils/minidiscord/handlers/CompleteHandler.py
create_machine_utils/minidiscord/handlers/CooldownErrors.py
create_machine_utils/minidiscord/handlers/ExtensionErrors.py
create_machine_utils/minidiscord/handlers/NotFoundErrors.py
create_machine_utils/minidiscord/handlers/PermissionErrors.py
create_machine_utils/minidiscord/handlers/WrongPlaceErrors.py
create_machine_utils/minidiscord/handlers/__init__.py
data/__init__.py
data/json.py
minidiscord/__init__.py
minidiscord/context.py
minidiscord/errors.py
minidiscord/input.py
minidiscord/handlers/ArgumentErrors.py
minidiscord/handlers/CompleteHandler.py
minidiscord/handlers/CooldownErrors.py
minidiscord/handlers/ExtensionErrors.py
minidiscord/handlers/NotFoundErrors.py
minidiscord/handlers/PermissionErrors.py
minidiscord/handlers/WrongPlaceErrors.py
minidiscord/handlers/__init__.py
create_machine_utils-1.4.9.dist-info/LICENSE
create_machine_utils-1.4.9.dist-info/METADATA
create_machine_utils-1.4.9.dist-info/WHEEL
create_machine_utils-1.4.9.dist-info/top_level.txt
create_machine_utils-1.4.9.dist-info/RECORD
