Metadata-Version: 2.1
Name: create-machine-utils
Version: 1.4.9
Summary: The MiniUtils module to make making discord bots easier
Home-page: https://github.com/Minion3665/MiniUtils
Author: Minion3665
Author-email: nathan@clicksminuteper.net
License: GNU General Public License V3
Platform: UNKNOWN
Requires-Dist: Deprecated
Requires-Dist: discord.py
